TOPSIS_AyushJain_101803690/__init__.py
TOPSIS_Ayush_Jain_101803690-0.0.4.dist-info/LICENSE
TOPSIS_Ayush_Jain_101803690-0.0.4.dist-info/METADATA
TOPSIS_Ayush_Jain_101803690-0.0.4.dist-info/WHEEL
TOPSIS_Ayush_Jain_101803690-0.0.4.dist-info/top_level.txt
TOPSIS_Ayush_Jain_101803690-0.0.4.dist-info/RECORD
