Metadata-Version: 2.1
Name: TOPSIS-Ayush-Jain-101803690
Version: 0.0.4
Summary: Implementation of TOPSIS
Home-page: https://github.com/pypa/TOPSIS_AyushJain
Author: Ayush Jain
Author-email: ayushjain1722@gmail.com
License: UNKNOWN
Keywords: topsis pandas rank
Platform: UNKNOWN
Classifier: Programming Language :: Python :: 3
Classifier: License :: OSI Approved :: MIT License
Classifier: Operating System :: OS Independent
Requires-Python: >=3.0
Requires-Dist: pandas
